{
  "feature": "jiraspecialist-webhook-ticket-creation",
  "feature_id": "FEAT-110",
  "spec": "sdd/specs/FEAT-110-jiraspecialist-webhook-ticket-creation.spec.md",
  "type": "feature",
  "base_branch": "dev",
  "created_at": null,
  "completed_at": "2026-04-21T20:28:00.218711+00:00",
  "tasks": [
    {
      "id": "TASK-808",
      "slug": "jira-webhook-reporter-payload",
      "title": "Enrich JiraWebhookHook reporter payload to a dict",
      "feature_id": "FEAT-110",
      "feature": "jiraspecialist-webhook-ticket-creation",
      "spec": "sdd/specs/FEAT-110-jiraspecialist-webhook-ticket-creation.spec.md",
      "status": "done",
      "priority": "high",
      "effort": "S",
      "depends_on": [],
      "parallel": true,
      "parallelism_notes": "Touches core/hooks/jira_webhook.py only; shares no files with TASK-809.",
      "assigned_to": null,
      "started_at": "2026-04-21T18:33:25.330102+00:00",
      "completed_at": "2026-04-21T18:48:00.762947+00:00",
      "file": "sdd/tasks/completed/TASK-808-jira-webhook-reporter-payload.md"
    },
    {
      "id": "TASK-809",
      "slug": "jira-allowed-reporters-config",
      "title": "Add JIRA_ALLOWED_REPORTERS / JIRA_DEFAULT_REPORTER config constants",
      "feature_id": "FEAT-110",
      "feature": "jiraspecialist-webhook-ticket-creation",
      "spec": "sdd/specs/FEAT-110-jiraspecialist-webhook-ticket-creation.spec.md",
      "status": "done",
      "priority": "high",
      "effort": "S",
      "depends_on": [],
      "parallel": true,
      "parallelism_notes": "Touches parrot/conf.py only; shares no files with TASK-808. Both can land in any order before TASK-810.",
      "assigned_to": null,
      "started_at": "2026-04-21T18:33:25.330102+00:00",
      "completed_at": "2026-04-21T20:13:53.592766+00:00",
      "file": "sdd/tasks/completed/TASK-809-jira-allowed-reporters-config.md"
    },
    {
      "id": "TASK-810",
      "slug": "jira-ticket-created-handler",
      "title": "Implement handle_jira_ticket_created + route jira.created + update assignment caller",
      "feature_id": "FEAT-110",
      "feature": "jiraspecialist-webhook-ticket-creation",
      "spec": "sdd/specs/FEAT-110-jiraspecialist-webhook-ticket-creation.spec.md",
      "status": "done",
      "priority": "high",
      "effort": "M",
      "depends_on": [
        "TASK-808",
        "TASK-809"
      ],
      "parallel": false,
      "parallelism_notes": "Imports the config constants from TASK-809 and consumes the payload shape from TASK-808; must run after both.",
      "assigned_to": null,
      "started_at": "2026-04-21T18:33:25.330102+00:00",
      "completed_at": "2026-04-21T20:16:36.750139+00:00",
      "file": "sdd/tasks/completed/TASK-810-jira-ticket-created-handler.md"
    },
    {
      "id": "TASK-811",
      "slug": "jira-ticket-created-tests",
      "title": "Unit tests for ticket-created handler + webhook payload shape",
      "feature_id": "FEAT-110",
      "feature": "jiraspecialist-webhook-ticket-creation",
      "spec": "sdd/specs/FEAT-110-jiraspecialist-webhook-ticket-creation.spec.md",
      "status": "done",
      "priority": "high",
      "effort": "M",
      "depends_on": [
        "TASK-810"
      ],
      "parallel": false,
      "parallelism_notes": "Exercises the handler added in TASK-810; must run last.",
      "assigned_to": null,
      "started_at": "2026-04-21T18:33:25.330102+00:00",
      "completed_at": "2026-04-21T20:28:00.218711+00:00",
      "file": "sdd/tasks/completed/TASK-811-jira-ticket-created-tests.md"
    }
  ]
}
